specsuite/__init__.py
specsuite/extraction.py
specsuite/loading.py
specsuite/throughput.py
specsuite/utils.py
specsuite/warping.py
specsuite/wavecal.py
specsuite/widget.py
specsuite-1.1.0.dist-info/licenses/LICENSE
specsuite-1.1.0.dist-info/METADATA
specsuite-1.1.0.dist-info/WHEEL
specsuite-1.1.0.dist-info/top_level.txt
specsuite-1.1.0.dist-info/RECORD
