Metadata-Version: 2.4
Name: specsuite
Version: 1.1.0
Summary: A toolbox for processing data from long-slit spectrographs
Home-page: https://github.com/Autumn10677/specsuite
Author: Autumn Stephens
Author-email: aust8150@colorado.edu
License: MIT License
Project-URL: Homepage, https://github.com/Autumn10677/specsuite
Project-URL: Repository, https://github.com/Autumn10677/specsuite
Classifier: Programming Language :: Python :: 3
Classifier: License :: OSI Approved :: MIT License
Classifier: Operating System :: OS Independent
Requires-Python: >=3.10
License-File: LICENSE
Requires-Dist: lxml
Requires-Dist: astropy>=7.0
Requires-Dist: ipywidgets>=8.0
Requires-Dist: ipympl
Requires-Dist: joblib>=1.0
Requires-Dist: matplotlib>=3.0
Requires-Dist: numpy<2,>=1.26
Requires-Dist: pandas>=2.0
Requires-Dist: requests>=2.0
Requires-Dist: scipy>=1.0
Requires-Dist: tqdm>=4.0
Provides-Extra: dev
Requires-Dist: black; extra == "dev"
Requires-Dist: flake8; extra == "dev"
Requires-Dist: snakemake; extra == "dev"
Provides-Extra: docs
Requires-Dist: mkdocs; extra == "docs"
Requires-Dist: mkdocs-jupyter; extra == "docs"
Dynamic: author-email
Dynamic: home-page
Dynamic: license-file
